setup.py
hptcad/__init__.py
hptcad.egg-info/PKG-INFO
hptcad.egg-info/SOURCES.txt
hptcad.egg-info/dependency_links.txt
hptcad.egg-info/not-zip-safe
hptcad.egg-info/top_level.txt