Metadata-Version: 1.0
Name: hptcad
Version: 0.0.1
Summary: HPTCAD
Home-page: http://github.com/manstetten/hptcad
Author: Paul Manstetten
Author-email: manstetten@iue.tuwien.ac.at
License: MIT
Platform: UNKNOWN
